README
setup.py
cropresize2/__init__.py
cropresize2.egg-info/PKG-INFO
cropresize2.egg-info/SOURCES.txt
cropresize2.egg-info/dependency_links.txt
cropresize2.egg-info/entry_points.txt
cropresize2.egg-info/not-zip-safe
cropresize2.egg-info/requires.txt
cropresize2.egg-info/top_level.txt