Metadata-Version: 1.0
Name: cropresize2
Version: 0.1.8
Summary: crop and resize an image without doing the math yourself
Home-page: http://pypi.python.org/pypi/cropresize2
Author: Jeff Hammel, Vlad Frolov
Author-email: k0scist@gmail.com, frolvlad@gmail.com
License: GPL
Keywords: image
Platform: UNKNOWN
